LICENSE.txt
setup.cfg
setup.py
atcfglodqvgauwzlnk/__init__.py
atcfglodqvgauwzlnk.egg-info/PKG-INFO
atcfglodqvgauwzlnk.egg-info/SOURCES.txt
atcfglodqvgauwzlnk.egg-info/dependency_links.txt
atcfglodqvgauwzlnk.egg-info/requires.txt
atcfglodqvgauwzlnk.egg-info/top_level.txt