Metadata-Version: 2.1
Name: atcfglodqvgauwzlnk
Version: 0.5.5
Summary: a tool to operate coco dataset file
Home-page: UNKNOWN
Author: qzhu
Author-email: qzhu.working@gmail.com
License: UNKNOWN
Platform: UNKNOWN
Requires-Python: >=3.6
License-File: LICENSE.txt
